projex/__init__.py
projex/_version.py
projex/addon.py
projex/callbacks.py
projex/cli.py
projex/contexts.py
projex/dataset.py
projex/dates.py
projex/decorators.py
projex/enum.py
projex/envmanager.py
projex/errors.py
projex/funcutil.py
projex/hooks.py
projex/init.py
projex/iters.py
projex/lazymodule.py
projex/locks.py
projex/makotext.py
projex/money.py
projex/notify.py
projex/plugin.py
projex/pyi.py
projex/pyi_hook.py
projex/regex.py
projex/rest.py
projex/scaffold.py
projex/security.py
projex/sorting.py
projex/text.py
projex/urls.py
projex/versioning.py
projex/xmlutil.py
projex/xos.py
projex/resources/__init__.py
projex/resources/img/installer-side.bmp
projex/resources/img/installer.bmp
projex/resources/img/logo.ico
projex/resources/img/logo_128.png
projex/resources/img/logo_16.png
projex/resources/img/logo_32.png
projex/resources/img/logo_64.png
projex/resources/img/logo_blog_wide.png
projex/resources/img/logo_dark_128.png
projex/resources/img/logo_dark_16.png
projex/resources/img/logo_dark_32.png
projex/resources/img/logo_dark_64.png
projex/resources/img/logo_dark_wide.png
projex/resources/img/logo_dev_wide.png
projex/resources/img/logo_dev_wide_white.png
projex/resources/img/logo_docs_wide.png
projex/resources/img/logo_wide.png
projex/resources/licenses/GPL.txt
projex/resources/licenses/LGPL.txt
projex/scripts/xbuild.py
projex/wikitext/__init__.py
projex/wikitext/commands.py
projex/wikitext/styles.py
projex/wikitext/urlhandler.py
projex/xbuild/__init__.py
projex/xbuild/builder.py
projex/xbuild/errors.py
projex/xbuild/templ.py
projex-2015.0.13.data/scripts/xbuild.py
projex-2015.0.13.dist-info/DESCRIPTION.rst
projex-2015.0.13.dist-info/METADATA
projex-2015.0.13.dist-info/metadata.json
projex-2015.0.13.dist-info/RECORD
projex-2015.0.13.dist-info/top_level.txt
projex-2015.0.13.dist-info/WHEEL
