Metadata-Version: 2.0
Name: projex
Version: 2015.0.13
Summary: Library of useful utilities for Python.
Home-page: https://github.com/ProjexSoftware/projex
Author: Eric Hulser
Author-email: eric.hulser@gmail.com
License: MIT
Platform: UNKNOWN
